claude_usage_analyzer/__init__.py
claude_usage_analyzer/analytics.py
claude_usage_analyzer/cli.py
claude_usage_analyzer/parser.py
claude_usage_analyzer/pricing.py
claude_usage_analyzer/pricing_fetcher.py
claude_usage_analyzer-0.4.0.dist-info/METADATA
claude_usage_analyzer-0.4.0.dist-info/WHEEL
claude_usage_analyzer-0.4.0.dist-info/entry_points.txt
claude_usage_analyzer-0.4.0.dist-info/licenses/LICENSE
claude_usage_analyzer-0.4.0.dist-info/RECORD
